{
  "country": "ie",
  "currency": "EUR",
  "top10": [
    {
      "rank": 1,
      "title": "Surgeons / Doctors",
      "salaryMin": 20922,
      "salaryMax": 68433,
      "description": "Surgeons top the list of the highest paying careers due to the critical nature of their job. A surgeon's profession involves high risk and requires extensive knowledge and a long learning path; the necessary ingredients for a high paying career.",
      "reasons": [
        "high risk job",
        "extensive knowledge",
        "high perceived value",
        "revenue generator"
      ]
    },
    {
      "rank": 2,
      "title": "Judges",
      "salaryMin": 17581,
      "salaryMax": 57536,
      "description": "Judges earn quite high salaries because of the huge responsibilities associated with their job. Deciding people's fates is not an easy task and the high wage is perfectly justified.",
      "reasons": [
        "high responsibility job",
        "extensive knowledge"
      ]
    },
    {
      "rank": 3,
      "title": "Lawyers",
      "salaryMin": 14239,
      "salaryMax": 46639,
      "description": "The main reason that lawyers earn big wages is because of their high perceived value in the eyes of their clients. A successful lawyer can save/earn you tons of money or can possibly spare you a death sentence.",
      "reasons": [
        "high perceived value",
        "extensive knowledge",
        "revenue generator"
      ]
    },
    {
      "rank": 4,
      "title": "Bank Managers",
      "salaryMin": 13411,
      "salaryMax": 43879,
      "description": "Being in charge of hundreds of millions in funds and investments with all the associated risks that come along makes managing a bank an extremely critical task worthy of a large salary.",
      "reasons": [
        "high risk",
        "high responsibility job",
        "huge impact"
      ]
    },
    {
      "rank": 5,
      "title": "Chief Executive Officers",
      "salaryMin": 12568,
      "salaryMax": 41118,
      "description": "CEOs are primarily responsible for the success or failure of complete organizations. Their huge remuneration is due to the vast scope of impact as well as the risks involved.",
      "reasons": [
        "widespread impact",
        "leadership position",
        "high risk"
      ]
    },
    {
      "rank": 6,
      "title": "Chief Financial Officers",
      "salaryMin": 11725,
      "salaryMax": 38358,
      "description": "Any job that is about managing money automatically qualifies for high pay. CFOs manage budgets, spending, costs, and revenue which directly impacts the operations of the organization.",
      "reasons": [
        "high risk",
        "extensive experience",
        "high responsibility job"
      ]
    },
    {
      "rank": 7,
      "title": "Orthodontists",
      "salaryMin": 11304,
      "salaryMax": 37050,
      "description": "Orthodontists operate in an industry where people are willing to pay high costs for a service, which directly makes Orthodontists among the best paying jobs.",
      "reasons": [
        "high cost industry",
        "high level knowledge",
        "high perceived value",
        "revenue generator"
      ]
    },
    {
      "rank": 8,
      "title": "College Professors",
      "salaryMin": 10054,
      "salaryMax": 32836,
      "description": "College professors are among the top-earning and most prestigious careers. Becoming a professor is not easy and requires persistence which is partly why they earn so high.",
      "reasons": [
        "high level knowledge",
        "high perceived value",
        "revenue generator"
      ]
    },
    {
      "rank": 9,
      "title": "Pilots",
      "salaryMin": 8383,
      "salaryMax": 27461,
      "description": "Probably the only career on the list that involves some kind of excitement, nevertheless; pilots undergo rigorous training programs and they are responsible for the safety of thousands of people every day.",
      "reasons": [
        "high risk",
        "extensive experience"
      ]
    },
    {
      "rank": 10,
      "title": "Marketing Directors",
      "salaryMin": 7541,
      "salaryMax": 24700,
      "description": "Marketing directors are in charge of increasing the revenue of their organizations. They are directly responsible for generating business and they are well paid for that reason.",
      "reasons": [
        "revenue generator"
      ]
    }
  ],
  "jobs": {
    "ai-machine-learning": [
      {
        "rank": 1,
        "title": "AI Research Scientist",
        "salaryMin": 26153,
        "salaryMax": 26153,
        "reasons": []
      },
      {
        "rank": 2,
        "title": "Machine Learning Engineer",
        "salaryMin": 24409,
        "salaryMax": 24409,
        "reasons": []
      },
      {
        "rank": 3,
        "title": "Deep Learning Engineer",
        "salaryMin": 22666,
        "salaryMax": 22666,
        "reasons": []
      },
      {
        "rank": 4,
        "title": "Computer Vision Engineer",
        "salaryMin": 20922,
        "salaryMax": 20922,
        "reasons": []
      },
      {
        "rank": 5,
        "title": "NLP Engineer",
        "salaryMin": 20051,
        "salaryMax": 20051,
        "reasons": []
      },
      {
        "rank": 6,
        "title": "AI Product Manager",
        "salaryMin": 19179,
        "salaryMax": 19179,
        "reasons": []
      },
      {
        "rank": 7,
        "title": "Data Scientist",
        "salaryMin": 18307,
        "salaryMax": 18307,
        "reasons": []
      },
      {
        "rank": 8,
        "title": "AI Ethics Officer",
        "salaryMin": 17435,
        "salaryMax": 17435,
        "reasons": []
      },
      {
        "rank": 9,
        "title": "ML Operations Engineer",
        "salaryMin": 16564,
        "salaryMax": 16564,
        "reasons": []
      },
      {
        "rank": 10,
        "title": "Business Intelligence Developer",
        "salaryMin": 15692,
        "salaryMax": 15692,
        "reasons": []
      }
    ],
    "finance-accounting": [
      {
        "rank": 1,
        "title": "Finance Director",
        "salaryMin": 24264,
        "salaryMax": 24264,
        "reasons": []
      },
      {
        "rank": 2,
        "title": "Financial Manager",
        "salaryMin": 23102,
        "salaryMax": 23102,
        "reasons": []
      },
      {
        "rank": 3,
        "title": "Investment Advisor",
        "salaryMin": 21939,
        "salaryMax": 21939,
        "reasons": []
      },
      {
        "rank": 4,
        "title": "Risk Management Director",
        "salaryMin": 19760,
        "salaryMax": 19760,
        "reasons": []
      },
      {
        "rank": 5,
        "title": "Economist",
        "salaryMin": 19179,
        "salaryMax": 19179,
        "reasons": []
      },
      {
        "rank": 6,
        "title": "Tax Director",
        "salaryMin": 19034,
        "salaryMax": 19034,
        "reasons": []
      },
      {
        "rank": 7,
        "title": "Audit Director",
        "salaryMin": 18888,
        "salaryMax": 18888,
        "reasons": []
      },
      {
        "rank": 8,
        "title": "Investment Fund Manager",
        "salaryMin": 18307,
        "salaryMax": 18307,
        "reasons": []
      },
      {
        "rank": 9,
        "title": "Accounting Manager",
        "salaryMin": 17435,
        "salaryMax": 17435,
        "reasons": []
      },
      {
        "rank": 10,
        "title": "Auditing Manager",
        "salaryMin": 17145,
        "salaryMax": 17145,
        "reasons": []
      }
    ],
    "business-administration": [
      {
        "rank": 1,
        "title": "Chief Executive Officer",
        "salaryMin": 26153,
        "salaryMax": 26153,
        "reasons": []
      },
      {
        "rank": 2,
        "title": "Chairman of The Board",
        "salaryMin": 25426,
        "salaryMax": 25426,
        "reasons": []
      },
      {
        "rank": 3,
        "title": "Chief Financial Officer",
        "salaryMin": 24119,
        "salaryMax": 24119,
        "reasons": []
      },
      {
        "rank": 4,
        "title": "Regional Director",
        "salaryMin": 23247,
        "salaryMax": 23247,
        "reasons": []
      },
      {
        "rank": 5,
        "title": "Executive Manager",
        "salaryMin": 21213,
        "salaryMax": 21213,
        "reasons": []
      },
      {
        "rank": 6,
        "title": "Chief Corporate Officer",
        "salaryMin": 21068,
        "salaryMax": 21068,
        "reasons": []
      },
      {
        "rank": 7,
        "title": "Managing Director",
        "salaryMin": 20922,
        "salaryMax": 20922,
        "reasons": []
      },
      {
        "rank": 8,
        "title": "General Manager",
        "salaryMin": 20341,
        "salaryMax": 20341,
        "reasons": []
      },
      {
        "rank": 9,
        "title": "Risk and Capital Manager",
        "salaryMin": 19760,
        "salaryMax": 19760,
        "reasons": []
      },
      {
        "rank": 10,
        "title": "Chief Operating Officer",
        "salaryMin": 19615,
        "salaryMax": 19615,
        "reasons": []
      }
    ],
    "advertising": [
      {
        "rank": 1,
        "title": "Advertising Sales Director",
        "salaryMin": 20051,
        "salaryMax": 20051,
        "reasons": []
      },
      {
        "rank": 2,
        "title": "Events Director",
        "salaryMin": 19615,
        "salaryMax": 19615,
        "reasons": []
      },
      {
        "rank": 3,
        "title": "Advertising Manager",
        "salaryMin": 18743,
        "salaryMax": 18743,
        "reasons": []
      },
      {
        "rank": 4,
        "title": "Product and Brand Manager",
        "salaryMin": 18307,
        "salaryMax": 18307,
        "reasons": []
      },
      {
        "rank": 5,
        "title": "Sales Promotion Manager",
        "salaryMin": 18162,
        "salaryMax": 18162,
        "reasons": []
      },
      {
        "rank": 6,
        "title": "Media Production Manager",
        "salaryMin": 15692,
        "salaryMax": 15692,
        "reasons": []
      },
      {
        "rank": 7,
        "title": "Media Sales Executive",
        "salaryMin": 14965,
        "salaryMax": 14965,
        "reasons": []
      },
      {
        "rank": 8,
        "title": "Social Media Manager",
        "salaryMin": 14820,
        "salaryMax": 14820,
        "reasons": []
      },
      {
        "rank": 9,
        "title": "Digital Media Strategist",
        "salaryMin": 14311,
        "salaryMax": 14311,
        "reasons": []
      },
      {
        "rank": 10,
        "title": "Advertising Account Manager",
        "salaryMin": 13963,
        "salaryMax": 13963,
        "reasons": []
      }
    ],
    "architecture": [
      {
        "rank": 1,
        "title": "Architectural Manager",
        "salaryMin": 20922,
        "salaryMax": 20922,
        "reasons": []
      },
      {
        "rank": 2,
        "title": "Architecture Consultant",
        "salaryMin": 20051,
        "salaryMax": 20051,
        "reasons": []
      },
      {
        "rank": 3,
        "title": "Assistant Architectural Manager",
        "salaryMin": 19760,
        "salaryMax": 19760,
        "reasons": []
      },
      {
        "rank": 4,
        "title": "Facilities and Project Manager",
        "salaryMin": 19179,
        "salaryMax": 19179,
        "reasons": []
      },
      {
        "rank": 5,
        "title": "Design Manager",
        "salaryMin": 18888,
        "salaryMax": 18888,
        "reasons": []
      },
      {
        "rank": 6,
        "title": "Landscape Architect",
        "salaryMin": 16273,
        "salaryMax": 16273,
        "reasons": []
      },
      {
        "rank": 7,
        "title": "Architecture Estimating Manager",
        "salaryMin": 15692,
        "salaryMax": 15692,
        "reasons": []
      },
      {
        "rank": 8,
        "title": "Architect",
        "salaryMin": 13963,
        "salaryMax": 13963,
        "reasons": []
      },
      {
        "rank": 9,
        "title": "Architectural Designer",
        "salaryMin": 13265,
        "salaryMax": 13265,
        "reasons": []
      },
      {
        "rank": 10,
        "title": "CAD Manager",
        "salaryMin": 13091,
        "salaryMax": 13091,
        "reasons": []
      }
    ],
    "automotive": [
      {
        "rank": 1,
        "title": "Regional Manager",
        "salaryMin": 22666,
        "salaryMax": 22666,
        "reasons": []
      },
      {
        "rank": 2,
        "title": "Automotive General Manager",
        "salaryMin": 21794,
        "salaryMax": 21794,
        "reasons": []
      },
      {
        "rank": 3,
        "title": "Automotive Branch Manager",
        "salaryMin": 18307,
        "salaryMax": 18307,
        "reasons": []
      },
      {
        "rank": 4,
        "title": "Automotive Purchase Manager",
        "salaryMin": 17145,
        "salaryMax": 17145,
        "reasons": []
      },
      {
        "rank": 5,
        "title": "Purchasing Project Manager",
        "salaryMin": 16273,
        "salaryMax": 16273,
        "reasons": []
      },
      {
        "rank": 6,
        "title": "Automotive Project Manager",
        "salaryMin": 15546,
        "salaryMax": 15546,
        "reasons": []
      },
      {
        "rank": 7,
        "title": "Auto Parts Manager",
        "salaryMin": 14820,
        "salaryMax": 14820,
        "reasons": []
      },
      {
        "rank": 8,
        "title": "Automotive Assembly Manager",
        "salaryMin": 13614,
        "salaryMax": 13614,
        "reasons": []
      },
      {
        "rank": 9,
        "title": "Service Manager",
        "salaryMin": 13091,
        "salaryMax": 13091,
        "reasons": []
      },
      {
        "rank": 10,
        "title": "Used Car Manager",
        "salaryMin": 11696,
        "salaryMax": 11696,
        "reasons": []
      }
    ],
    "aviation": [
      {
        "rank": 1,
        "title": "Aviation Manager",
        "salaryMin": 24409,
        "salaryMax": 24409,
        "reasons": []
      },
      {
        "rank": 2,
        "title": "Airport Services Manager",
        "salaryMin": 24119,
        "salaryMax": 24119,
        "reasons": []
      },
      {
        "rank": 3,
        "title": "Airlines Sales Director",
        "salaryMin": 23538,
        "salaryMax": 23538,
        "reasons": []
      },
      {
        "rank": 4,
        "title": "Aviation Safety Manager",
        "salaryMin": 22666,
        "salaryMax": 22666,
        "reasons": []
      },
      {
        "rank": 5,
        "title": "Chief Pilot",
        "salaryMin": 20922,
        "salaryMax": 20922,
        "reasons": []
      },
      {
        "rank": 6,
        "title": "Aircraft Pilot",
        "salaryMin": 20051,
        "salaryMax": 20051,
        "reasons": []
      },
      {
        "rank": 7,
        "title": "Fleet Controller",
        "salaryMin": 18888,
        "salaryMax": 18888,
        "reasons": []
      },
      {
        "rank": 8,
        "title": "Airfield Management Specialist",
        "salaryMin": 18016,
        "salaryMax": 18016,
        "reasons": []
      },
      {
        "rank": 9,
        "title": "Aviation Analyst",
        "salaryMin": 15692,
        "salaryMax": 15692,
        "reasons": []
      },
      {
        "rank": 10,
        "title": "Aerospace Engineer",
        "salaryMin": 14820,
        "salaryMax": 14820,
        "reasons": []
      }
    ],
    "banking": [
      {
        "rank": 1,
        "title": "International Banking Manager",
        "salaryMin": 26153,
        "salaryMax": 26153,
        "reasons": []
      },
      {
        "rank": 2,
        "title": "Group Branch Manager",
        "salaryMin": 25862,
        "salaryMax": 25862,
        "reasons": []
      },
      {
        "rank": 3,
        "title": "Bank Regional Manager",
        "salaryMin": 25426,
        "salaryMax": 25426,
        "reasons": []
      },
      {
        "rank": 4,
        "title": "Bank Operations Head",
        "salaryMin": 24991,
        "salaryMax": 24991,
        "reasons": []
      },
      {
        "rank": 5,
        "title": "Capital Risk Manager",
        "salaryMin": 24264,
        "salaryMax": 24264,
        "reasons": []
      },
      {
        "rank": 6,
        "title": "Credit Portfolio Manager",
        "salaryMin": 23974,
        "salaryMax": 23974,
        "reasons": []
      },
      {
        "rank": 7,
        "title": "Internal Bank Audit Manager",
        "salaryMin": 23247,
        "salaryMax": 23247,
        "reasons": []
      },
      {
        "rank": 8,
        "title": "Cash Management Manager",
        "salaryMin": 22375,
        "salaryMax": 22375,
        "reasons": []
      },
      {
        "rank": 9,
        "title": "Online Banking Manager",
        "salaryMin": 21358,
        "salaryMax": 21358,
        "reasons": []
      },
      {
        "rank": 10,
        "title": "Mortgage Operations Manager",
        "salaryMin": 20922,
        "salaryMax": 20922,
        "reasons": []
      }
    ],
    "construction": [
      {
        "rank": 1,
        "title": "Construction Manager",
        "salaryMin": 20051,
        "salaryMax": 20051,
        "reasons": []
      },
      {
        "rank": 2,
        "title": "Construction Project Manager",
        "salaryMin": 19179,
        "salaryMax": 19179,
        "reasons": []
      },
      {
        "rank": 3,
        "title": "Construction Operations Manager",
        "salaryMin": 18307,
        "salaryMax": 18307,
        "reasons": []
      },
      {
        "rank": 4,
        "title": "Site Leader",
        "salaryMin": 17435,
        "salaryMax": 17435,
        "reasons": []
      },
      {
        "rank": 5,
        "title": "Building Contracts Manager",
        "salaryMin": 16564,
        "salaryMax": 16564,
        "reasons": []
      },
      {
        "rank": 6,
        "title": "Tender Manager",
        "salaryMin": 15837,
        "salaryMax": 15837,
        "reasons": []
      },
      {
        "rank": 7,
        "title": "Building Sales Manager",
        "salaryMin": 15546,
        "salaryMax": 15546,
        "reasons": []
      },
      {
        "rank": 8,
        "title": "Construction Quality Control Manager",
        "salaryMin": 14486,
        "salaryMax": 14486,
        "reasons": []
      },
      {
        "rank": 9,
        "title": "Purchasing Manager",
        "salaryMin": 13091,
        "salaryMax": 13091,
        "reasons": []
      },
      {
        "rank": 10,
        "title": "Installation Manager",
        "salaryMin": 12742,
        "salaryMax": 12742,
        "reasons": []
      }
    ],
    "counseling": [
      {
        "rank": 1,
        "title": "Psychologist",
        "salaryMin": 19179,
        "salaryMax": 19179,
        "reasons": []
      },
      {
        "rank": 2,
        "title": "Director of Rehabilitation Services",
        "salaryMin": 18307,
        "salaryMax": 18307,
        "reasons": []
      },
      {
        "rank": 3,
        "title": "Youth Development Manager",
        "salaryMin": 17435,
        "salaryMax": 17435,
        "reasons": []
      },
      {
        "rank": 4,
        "title": "Guidance Director",
        "salaryMin": 17145,
        "salaryMax": 17145,
        "reasons": []
      },
      {
        "rank": 5,
        "title": "Adoption Services Director",
        "salaryMin": 16418,
        "salaryMax": 16418,
        "reasons": []
      },
      {
        "rank": 6,
        "title": "Mental Health Counselor",
        "salaryMin": 15692,
        "salaryMax": 15692,
        "reasons": []
      },
      {
        "rank": 7,
        "title": "Supervising Counselor",
        "salaryMin": 14965,
        "salaryMax": 14965,
        "reasons": []
      },
      {
        "rank": 8,
        "title": "Family Support Specialist",
        "salaryMin": 14820,
        "salaryMax": 14820,
        "reasons": []
      },
      {
        "rank": 9,
        "title": "Youth Care Counselor",
        "salaryMin": 14675,
        "salaryMax": 14675,
        "reasons": []
      },
      {
        "rank": 10,
        "title": "Employment Counselor",
        "salaryMin": 13963,
        "salaryMax": 13963,
        "reasons": []
      }
    ],
    "customer-service": [
      {
        "rank": 1,
        "title": "Customer Service Manager",
        "salaryMin": 15692,
        "salaryMax": 15692,
        "reasons": []
      },
      {
        "rank": 2,
        "title": "Service Delivery Manager",
        "salaryMin": 15401,
        "salaryMax": 15401,
        "reasons": []
      },
      {
        "rank": 3,
        "title": "Regional Account Manager",
        "salaryMin": 14820,
        "salaryMax": 14820,
        "reasons": []
      },
      {
        "rank": 4,
        "title": "Customer Success Manager",
        "salaryMin": 14311,
        "salaryMax": 14311,
        "reasons": []
      },
      {
        "rank": 5,
        "title": "Call Center Manager",
        "salaryMin": 13963,
        "salaryMax": 13963,
        "reasons": []
      },
      {
        "rank": 6,
        "title": "Client Relationship Executive",
        "salaryMin": 13614,
        "salaryMax": 13614,
        "reasons": []
      },
      {
        "rank": 7,
        "title": "Operations Support Manager",
        "salaryMin": 13091,
        "salaryMax": 13091,
        "reasons": []
      },
      {
        "rank": 8,
        "title": "Customer Service Executive",
        "salaryMin": 10476,
        "salaryMax": 10476,
        "reasons": []
      },
      {
        "rank": 9,
        "title": "Customer Service Team Leader",
        "salaryMin": 9778,
        "salaryMax": 9778,
        "reasons": []
      },
      {
        "rank": 10,
        "title": "Customer Service Advisor",
        "salaryMin": 9604,
        "salaryMax": 9604,
        "reasons": []
      }
    ],
    "education-teaching": [
      {
        "rank": 1,
        "title": "College Dean",
        "salaryMin": 22666,
        "salaryMax": 22666,
        "reasons": []
      },
      {
        "rank": 2,
        "title": "Dean of Faculty",
        "salaryMin": 21358,
        "salaryMax": 21358,
        "reasons": []
      },
      {
        "rank": 3,
        "title": "Professor",
        "salaryMin": 20922,
        "salaryMax": 20922,
        "reasons": []
      },
      {
        "rank": 4,
        "title": "Lecturer",
        "salaryMin": 16564,
        "salaryMax": 16564,
        "reasons": []
      },
      {
        "rank": 5,
        "title": "Head of School",
        "salaryMin": 15982,
        "salaryMax": 15982,
        "reasons": []
      },
      {
        "rank": 6,
        "title": "Post Doctoral Researcher",
        "salaryMin": 15256,
        "salaryMax": 15256,
        "reasons": []
      },
      {
        "rank": 7,
        "title": "Educational Psychologist",
        "salaryMin": 15111,
        "salaryMax": 15111,
        "reasons": []
      },
      {
        "rank": 8,
        "title": "Academic Manager",
        "salaryMin": 14675,
        "salaryMax": 14675,
        "reasons": []
      },
      {
        "rank": 9,
        "title": "Clinical School Psychologist",
        "salaryMin": 14253,
        "salaryMax": 14253,
        "reasons": []
      },
      {
        "rank": 10,
        "title": "Principal",
        "salaryMin": 13963,
        "salaryMax": 13963,
        "reasons": []
      }
    ],
    "energy": [
      {
        "rank": 1,
        "title": "Operations Manager",
        "salaryMin": 24409,
        "salaryMax": 24409,
        "reasons": []
      },
      {
        "rank": 2,
        "title": "Geophysicist",
        "salaryMin": 19615,
        "salaryMax": 19615,
        "reasons": []
      },
      {
        "rank": 3,
        "title": "Engineering Geologist",
        "salaryMin": 19179,
        "salaryMax": 19179,
        "reasons": []
      },
      {
        "rank": 4,
        "title": "Exploration Manager",
        "salaryMin": 18743,
        "salaryMax": 18743,
        "reasons": []
      },
      {
        "rank": 5,
        "title": "Energy Dispatch Director",
        "salaryMin": 18452,
        "salaryMax": 18452,
        "reasons": []
      },
      {
        "rank": 6,
        "title": "Geothermal Production Manager",
        "salaryMin": 18016,
        "salaryMax": 18016,
        "reasons": []
      },
      {
        "rank": 7,
        "title": "Mining Project Manager",
        "salaryMin": 17726,
        "salaryMax": 17726,
        "reasons": []
      },
      {
        "rank": 8,
        "title": "Service Delivery Manager",
        "salaryMin": 17145,
        "salaryMax": 17145,
        "reasons": []
      },
      {
        "rank": 9,
        "title": "Sustainability Specialist",
        "salaryMin": 16564,
        "salaryMax": 16564,
        "reasons": []
      },
      {
        "rank": 10,
        "title": "Energy Advisor",
        "salaryMin": 15692,
        "salaryMax": 15692,
        "reasons": []
      }
    ],
    "engineering": [
      {
        "rank": 1,
        "title": "Director of Engineering",
        "salaryMin": 20922,
        "salaryMax": 20922,
        "reasons": []
      },
      {
        "rank": 2,
        "title": "Engineering Production Manager",
        "salaryMin": 18307,
        "salaryMax": 18307,
        "reasons": []
      },
      {
        "rank": 3,
        "title": "Field Engineering Manager",
        "salaryMin": 17435,
        "salaryMax": 17435,
        "reasons": []
      },
      {
        "rank": 4,
        "title": "Electrical Engineering Manager",
        "salaryMin": 15692,
        "salaryMax": 15692,
        "reasons": []
      },
      {
        "rank": 5,
        "title": "Engineering Key Account Manager",
        "salaryMin": 15401,
        "salaryMax": 15401,
        "reasons": []
      },
      {
        "rank": 6,
        "title": "Engineering Project Manager",
        "salaryMin": 14486,
        "salaryMax": 14486,
        "reasons": []
      },
      {
        "rank": 7,
        "title": "Mechanical Engineering Manager",
        "salaryMin": 13963,
        "salaryMax": 13963,
        "reasons": []
      },
      {
        "rank": 8,
        "title": "Engineering Sales Manager",
        "salaryMin": 13614,
        "salaryMax": 13614,
        "reasons": []
      },
      {
        "rank": 9,
        "title": "Engineering Consultant",
        "salaryMin": 13091,
        "salaryMax": 13091,
        "reasons": []
      },
      {
        "rank": 10,
        "title": "Chief Engineer",
        "salaryMin": 12829,
        "salaryMax": 12829,
        "reasons": []
      }
    ],
    "manufacturing": [
      {
        "rank": 1,
        "title": "Production Director",
        "salaryMin": 20051,
        "salaryMax": 20051,
        "reasons": []
      },
      {
        "rank": 2,
        "title": "Director of Manufacturing",
        "salaryMin": 19615,
        "salaryMax": 19615,
        "reasons": []
      },
      {
        "rank": 3,
        "title": "Industrial Production Manager",
        "salaryMin": 18888,
        "salaryMax": 18888,
        "reasons": []
      },
      {
        "rank": 4,
        "title": "Operational Excellence General Manager",
        "salaryMin": 18307,
        "salaryMax": 18307,
        "reasons": []
      },
      {
        "rank": 5,
        "title": "Technology Development Manager",
        "salaryMin": 18016,
        "salaryMax": 18016,
        "reasons": []
      },
      {
        "rank": 6,
        "title": "Manufacturing Manager",
        "salaryMin": 17435,
        "salaryMax": 17435,
        "reasons": []
      },
      {
        "rank": 7,
        "title": "Plant Manager",
        "salaryMin": 17145,
        "salaryMax": 17145,
        "reasons": []
      },
      {
        "rank": 8,
        "title": "Product Manager",
        "salaryMin": 16564,
        "salaryMax": 16564,
        "reasons": []
      },
      {
        "rank": 9,
        "title": "Shipping Manager",
        "salaryMin": 16273,
        "salaryMax": 16273,
        "reasons": []
      },
      {
        "rank": 10,
        "title": "Key Account Manager",
        "salaryMin": 15692,
        "salaryMax": 15692,
        "reasons": []
      }
    ],
    "fitness-sports": [
      {
        "rank": 1,
        "title": "Sports Manager",
        "salaryMin": 18743,
        "salaryMax": 18743,
        "reasons": []
      },
      {
        "rank": 2,
        "title": "Fitness Manager",
        "salaryMin": 17435,
        "salaryMax": 17435,
        "reasons": []
      },
      {
        "rank": 3,
        "title": "Head Coach",
        "salaryMin": 16564,
        "salaryMax": 16564,
        "reasons": []
      },
      {
        "rank": 4,
        "title": "Head Gymnastics Instructor",
        "salaryMin": 11347,
        "salaryMax": 11347,
        "reasons": []
      },
      {
        "rank": 5,
        "title": "Ski Instructor",
        "salaryMin": 9778,
        "salaryMax": 9778,
        "reasons": []
      },
      {
        "rank": 6,
        "title": "Assistant Coach",
        "salaryMin": 9604,
        "salaryMax": 9604,
        "reasons": []
      },
      {
        "rank": 7,
        "title": "Swim Instructor",
        "salaryMin": 9255,
        "salaryMax": 9255,
        "reasons": []
      },
      {
        "rank": 8,
        "title": "Personal Trainer",
        "salaryMin": 8907,
        "salaryMax": 8907,
        "reasons": []
      },
      {
        "rank": 9,
        "title": "Game Manager",
        "salaryMin": 8558,
        "salaryMax": 8558,
        "reasons": []
      },
      {
        "rank": 10,
        "title": "Fitness Trainer",
        "salaryMin": 8209,
        "salaryMax": 8209,
        "reasons": []
      }
    ],
    "hospitality": [
      {
        "rank": 1,
        "title": "Hospitality Director",
        "salaryMin": 21794,
        "salaryMax": 21794,
        "reasons": []
      },
      {
        "rank": 2,
        "title": "Hotel Manager",
        "salaryMin": 20922,
        "salaryMax": 20922,
        "reasons": []
      },
      {
        "rank": 3,
        "title": "Fleet Manager",
        "salaryMin": 18016,
        "salaryMax": 18016,
        "reasons": []
      },
      {
        "rank": 4,
        "title": "Cluster Director",
        "salaryMin": 17435,
        "salaryMax": 17435,
        "reasons": []
      },
      {
        "rank": 5,
        "title": "Regional Restaurant Manager",
        "salaryMin": 16564,
        "salaryMax": 16564,
        "reasons": []
      },
      {
        "rank": 6,
        "title": "Assistant Hospitality Manager",
        "salaryMin": 15837,
        "salaryMax": 15837,
        "reasons": []
      },
      {
        "rank": 7,
        "title": "Hotel Sales Manager",
        "salaryMin": 15692,
        "salaryMax": 15692,
        "reasons": []
      },
      {
        "rank": 8,
        "title": "Food Service Manager",
        "salaryMin": 14965,
        "salaryMax": 14965,
        "reasons": []
      },
      {
        "rank": 9,
        "title": "Restaurant Manager",
        "salaryMin": 14137,
        "salaryMax": 14137,
        "reasons": []
      },
      {
        "rank": 10,
        "title": "Room Reservations Manager",
        "salaryMin": 13963,
        "salaryMax": 13963,
        "reasons": []
      }
    ],
    "healthcare": [
      {
        "rank": 1,
        "title": "Surgeon - Heart Transplant",
        "salaryMin": 52306,
        "salaryMax": 52306,
        "reasons": []
      },
      {
        "rank": 2,
        "title": "Chief of Surgery",
        "salaryMin": 50562,
        "salaryMax": 50562,
        "reasons": []
      },
      {
        "rank": 3,
        "title": "Surgeon - Orthopedic",
        "salaryMin": 48819,
        "salaryMax": 48819,
        "reasons": []
      },
      {
        "rank": 4,
        "title": "Surgeon - Plastic Reconstructive",
        "salaryMin": 47075,
        "salaryMax": 47075,
        "reasons": []
      },
      {
        "rank": 5,
        "title": "Invasive Cardiologist",
        "salaryMin": 46494,
        "salaryMax": 46494,
        "reasons": []
      },
      {
        "rank": 6,
        "title": "Surgeon - Neurology",
        "salaryMin": 45041,
        "salaryMax": 45041,
        "reasons": []
      },
      {
        "rank": 7,
        "title": "Surgeon - Pediatric",
        "salaryMin": 40682,
        "salaryMax": 40682,
        "reasons": []
      },
      {
        "rank": 8,
        "title": "Urologist",
        "salaryMin": 38794,
        "salaryMax": 38794,
        "reasons": []
      },
      {
        "rank": 9,
        "title": "Internist",
        "salaryMin": 36324,
        "salaryMax": 36324,
        "reasons": []
      },
      {
        "rank": 10,
        "title": "Chief of Psychology",
        "salaryMin": 34580,
        "salaryMax": 34580,
        "reasons": []
      }
    ],
    "human-resources": [
      {
        "rank": 1,
        "title": "Chief People Officer",
        "salaryMin": 19179,
        "salaryMax": 19179,
        "reasons": []
      },
      {
        "rank": 2,
        "title": "Director of Talent Acquisition",
        "salaryMin": 18307,
        "salaryMax": 18307,
        "reasons": []
      },
      {
        "rank": 3,
        "title": "Human Resources Vice President",
        "salaryMin": 18016,
        "salaryMax": 18016,
        "reasons": []
      },
      {
        "rank": 4,
        "title": "Human Resources Manager",
        "salaryMin": 17435,
        "salaryMax": 17435,
        "reasons": []
      },
      {
        "rank": 5,
        "title": "Recruiting Manager",
        "salaryMin": 17145,
        "salaryMax": 17145,
        "reasons": []
      },
      {
        "rank": 6,
        "title": "Human Resources Development Manager",
        "salaryMin": 16564,
        "salaryMax": 16564,
        "reasons": []
      },
      {
        "rank": 7,
        "title": "Benefits Manager",
        "salaryMin": 15256,
        "salaryMax": 15256,
        "reasons": []
      },
      {
        "rank": 8,
        "title": "Labor Relations Director",
        "salaryMin": 14529,
        "salaryMax": 14529,
        "reasons": []
      },
      {
        "rank": 9,
        "title": "Human Resources Consultant",
        "salaryMin": 14137,
        "salaryMax": 14137,
        "reasons": []
      },
      {
        "rank": 10,
        "title": "Training Executive",
        "salaryMin": 13963,
        "salaryMax": 13963,
        "reasons": []
      }
    ],
    "import-export": [
      {
        "rank": 1,
        "title": "Import and Export Manager",
        "salaryMin": 18307,
        "salaryMax": 18307,
        "reasons": []
      },
      {
        "rank": 2,
        "title": "Exports Sales Manager",
        "salaryMin": 18016,
        "salaryMax": 18016,
        "reasons": []
      },
      {
        "rank": 3,
        "title": "Export Logistics Manager",
        "salaryMin": 16128,
        "salaryMax": 16128,
        "reasons": []
      },
      {
        "rank": 4,
        "title": "Import and Export Consultant",
        "salaryMin": 14529,
        "salaryMax": 14529,
        "reasons": []
      },
      {
        "rank": 5,
        "title": "Importation Supervisor",
        "salaryMin": 12219,
        "salaryMax": 12219,
        "reasons": []
      },
      {
        "rank": 6,
        "title": "Export Logistics Specialist",
        "salaryMin": 10824,
        "salaryMax": 10824,
        "reasons": []
      },
      {
        "rank": 7,
        "title": "Export Supervisor",
        "salaryMin": 10476,
        "salaryMax": 10476,
        "reasons": []
      },
      {
        "rank": 8,
        "title": "Logistics Analyst",
        "salaryMin": 9691,
        "salaryMax": 9691,
        "reasons": []
      },
      {
        "rank": 9,
        "title": "Logistics Administrator",
        "salaryMin": 9255,
        "salaryMax": 9255,
        "reasons": []
      },
      {
        "rank": 10,
        "title": "Global Forwarding Agent",
        "salaryMin": 8383,
        "salaryMax": 8383,
        "reasons": []
      }
    ],
    "insurance": [
      {
        "rank": 1,
        "title": "Risk Management Director",
        "salaryMin": 22666,
        "salaryMax": 22666,
        "reasons": []
      },
      {
        "rank": 2,
        "title": "Risk Modeling Manager",
        "salaryMin": 21794,
        "salaryMax": 21794,
        "reasons": []
      },
      {
        "rank": 3,
        "title": "Insurance Manager",
        "salaryMin": 20922,
        "salaryMax": 20922,
        "reasons": []
      },
      {
        "rank": 4,
        "title": "Insurance Sales Director",
        "salaryMin": 19179,
        "salaryMax": 19179,
        "reasons": []
      },
      {
        "rank": 5,
        "title": "Policy Change Director",
        "salaryMin": 18307,
        "salaryMax": 18307,
        "reasons": []
      },
      {
        "rank": 6,
        "title": "Auditing Insurance Manager",
        "salaryMin": 17435,
        "salaryMax": 17435,
        "reasons": []
      },
      {
        "rank": 7,
        "title": "Loss Prevention Manager",
        "salaryMin": 17145,
        "salaryMax": 17145,
        "reasons": []
      },
      {
        "rank": 8,
        "title": "Claims Manager",
        "salaryMin": 16564,
        "salaryMax": 16564,
        "reasons": []
      },
      {
        "rank": 9,
        "title": "Actuary",
        "salaryMin": 15692,
        "salaryMax": 15692,
        "reasons": []
      },
      {
        "rank": 10,
        "title": "Insurance Program Manager",
        "salaryMin": 15401,
        "salaryMax": 15401,
        "reasons": []
      }
    ],
    "information-technology": [
      {
        "rank": 1,
        "title": "Chief Information Officer",
        "salaryMin": 19179,
        "salaryMax": 19179,
        "reasons": []
      },
      {
        "rank": 2,
        "title": "Online Banking Manager",
        "salaryMin": 18307,
        "salaryMax": 18307,
        "reasons": []
      },
      {
        "rank": 3,
        "title": "Information Technology Project Manager",
        "salaryMin": 17435,
        "salaryMax": 17435,
        "reasons": []
      },
      {
        "rank": 4,
        "title": "Enterprise Infrastructure Manager",
        "salaryMin": 16999,
        "salaryMax": 16999,
        "reasons": []
      },
      {
        "rank": 5,
        "title": "Director of Application Development",
        "salaryMin": 16564,
        "salaryMax": 16564,
        "reasons": []
      },
      {
        "rank": 6,
        "title": "Chief Information Security Officer",
        "salaryMin": 16273,
        "salaryMax": 16273,
        "reasons": []
      },
      {
        "rank": 7,
        "title": "Web Security Manager",
        "salaryMin": 16128,
        "salaryMax": 16128,
        "reasons": []
      },
      {
        "rank": 8,
        "title": "Business Intelligence Consultant",
        "salaryMin": 15837,
        "salaryMax": 15837,
        "reasons": []
      },
      {
        "rank": 9,
        "title": "Technical Project Manager",
        "salaryMin": 15546,
        "salaryMax": 15546,
        "reasons": []
      },
      {
        "rank": 10,
        "title": "Information Technology Sales Manager",
        "salaryMin": 15401,
        "salaryMax": 15401,
        "reasons": []
      }
    ],
    "law-legal": [
      {
        "rank": 1,
        "title": "Supreme Court Judge",
        "salaryMin": 34871,
        "salaryMax": 34871,
        "reasons": []
      },
      {
        "rank": 2,
        "title": "Administrative Law Judge",
        "salaryMin": 31384,
        "salaryMax": 31384,
        "reasons": []
      },
      {
        "rank": 3,
        "title": "Crown Prosecution Service Lawyer",
        "salaryMin": 29640,
        "salaryMax": 29640,
        "reasons": []
      },
      {
        "rank": 4,
        "title": "General Counsel",
        "salaryMin": 27896,
        "salaryMax": 27896,
        "reasons": []
      },
      {
        "rank": 5,
        "title": "Litigation Attorney",
        "salaryMin": 26153,
        "salaryMax": 26153,
        "reasons": []
      },
      {
        "rank": 6,
        "title": "Legal Services Director",
        "salaryMin": 25281,
        "salaryMax": 25281,
        "reasons": []
      },
      {
        "rank": 7,
        "title": "Judge Advocate",
        "salaryMin": 24409,
        "salaryMax": 24409,
        "reasons": []
      },
      {
        "rank": 8,
        "title": "Attorney",
        "salaryMin": 22666,
        "salaryMax": 22666,
        "reasons": []
      },
      {
        "rank": 9,
        "title": "Legal Executive",
        "salaryMin": 20922,
        "salaryMax": 20922,
        "reasons": []
      },
      {
        "rank": 10,
        "title": "Corporate Counsel",
        "salaryMin": 16564,
        "salaryMax": 16564,
        "reasons": []
      }
    ],
    "marketing": [
      {
        "rank": 1,
        "title": "Brand Director",
        "salaryMin": 21794,
        "salaryMax": 21794,
        "reasons": []
      },
      {
        "rank": 2,
        "title": "Chief Marketing Officer",
        "salaryMin": 20922,
        "salaryMax": 20922,
        "reasons": []
      },
      {
        "rank": 3,
        "title": "Brand Manager",
        "salaryMin": 20051,
        "salaryMax": 20051,
        "reasons": []
      },
      {
        "rank": 4,
        "title": "Marketing Manager",
        "salaryMin": 19179,
        "salaryMax": 19179,
        "reasons": []
      },
      {
        "rank": 5,
        "title": "Chief Product Officer",
        "salaryMin": 18888,
        "salaryMax": 18888,
        "reasons": []
      },
      {
        "rank": 6,
        "title": "Search Marketing Strategist",
        "salaryMin": 17145,
        "salaryMax": 17145,
        "reasons": []
      },
      {
        "rank": 7,
        "title": "Market Development Manager",
        "salaryMin": 16564,
        "salaryMax": 16564,
        "reasons": []
      },
      {
        "rank": 8,
        "title": "Product Manager",
        "salaryMin": 16273,
        "salaryMax": 16273,
        "reasons": []
      },
      {
        "rank": 9,
        "title": "Digital Marketing Manager",
        "salaryMin": 15982,
        "salaryMax": 15982,
        "reasons": []
      },
      {
        "rank": 10,
        "title": "Trade Marketing Executive",
        "salaryMin": 15692,
        "salaryMax": 15692,
        "reasons": []
      }
    ],
    "pharmaceutical-biotech": [
      {
        "rank": 1,
        "title": "Pharmaceutical Manufacturing Lead",
        "salaryMin": 27896,
        "salaryMax": 27896,
        "reasons": []
      },
      {
        "rank": 2,
        "title": "Pharmaceutical Manager",
        "salaryMin": 26153,
        "salaryMax": 26153,
        "reasons": []
      },
      {
        "rank": 3,
        "title": "Molecular and Cellular Biologist",
        "salaryMin": 24845,
        "salaryMax": 24845,
        "reasons": []
      },
      {
        "rank": 4,
        "title": "Medical Affairs Director",
        "salaryMin": 23538,
        "salaryMax": 23538,
        "reasons": []
      },
      {
        "rank": 5,
        "title": "Pharmaceutical Supply Chain Manager",
        "salaryMin": 23392,
        "salaryMax": 23392,
        "reasons": []
      },
      {
        "rank": 6,
        "title": "Bioinformatics Scientist",
        "salaryMin": 22666,
        "salaryMax": 22666,
        "reasons": []
      },
      {
        "rank": 7,
        "title": "Pharmaceutical Research Scientist",
        "salaryMin": 22375,
        "salaryMax": 22375,
        "reasons": []
      },
      {
        "rank": 8,
        "title": "Pharmaceutical Sales Manager",
        "salaryMin": 21794,
        "salaryMax": 21794,
        "reasons": []
      },
      {
        "rank": 9,
        "title": "Clinical Research Manager",
        "salaryMin": 21504,
        "salaryMax": 21504,
        "reasons": []
      },
      {
        "rank": 10,
        "title": "Pharmacy Manager",
        "salaryMin": 20922,
        "salaryMax": 20922,
        "reasons": []
      }
    ],
    "public-relations": [
      {
        "rank": 1,
        "title": "Head of Public Relations",
        "salaryMin": 19615,
        "salaryMax": 19615,
        "reasons": []
      },
      {
        "rank": 2,
        "title": "Public Relations Manager",
        "salaryMin": 17435,
        "salaryMax": 17435,
        "reasons": []
      },
      {
        "rank": 3,
        "title": "Director of Communications",
        "salaryMin": 16709,
        "salaryMax": 16709,
        "reasons": []
      },
      {
        "rank": 4,
        "title": "Head of Communications",
        "salaryMin": 16273,
        "salaryMax": 16273,
        "reasons": []
      },
      {
        "rank": 5,
        "title": "Marketing Communications Executive",
        "salaryMin": 15837,
        "salaryMax": 15837,
        "reasons": []
      },
      {
        "rank": 6,
        "title": "Public Relations Executive",
        "salaryMin": 15401,
        "salaryMax": 15401,
        "reasons": []
      },
      {
        "rank": 7,
        "title": "Media Relations Specialist",
        "salaryMin": 14486,
        "salaryMax": 14486,
        "reasons": []
      },
      {
        "rank": 8,
        "title": "Communications Project Manager",
        "salaryMin": 13963,
        "salaryMax": 13963,
        "reasons": []
      },
      {
        "rank": 9,
        "title": "Investor Relations Officer",
        "salaryMin": 12219,
        "salaryMax": 12219,
        "reasons": []
      },
      {
        "rank": 10,
        "title": "Government Relations Officer",
        "salaryMin": 10912,
        "salaryMax": 10912,
        "reasons": []
      }
    ],
    "procurement": [
      {
        "rank": 1,
        "title": "Supply Chain Director",
        "salaryMin": 21794,
        "salaryMax": 21794,
        "reasons": []
      },
      {
        "rank": 2,
        "title": "Procurement Manager",
        "salaryMin": 20922,
        "salaryMax": 20922,
        "reasons": []
      },
      {
        "rank": 3,
        "title": "Distribution Manager",
        "salaryMin": 20051,
        "salaryMax": 20051,
        "reasons": []
      },
      {
        "rank": 4,
        "title": "Warehouse Manager",
        "salaryMin": 18307,
        "salaryMax": 18307,
        "reasons": []
      },
      {
        "rank": 5,
        "title": "Vendor Manager",
        "salaryMin": 16564,
        "salaryMax": 16564,
        "reasons": []
      },
      {
        "rank": 6,
        "title": "Wholesale Buyer",
        "salaryMin": 15692,
        "salaryMax": 15692,
        "reasons": []
      },
      {
        "rank": 7,
        "title": "Supply Chain Analyst",
        "salaryMin": 14820,
        "salaryMax": 14820,
        "reasons": []
      },
      {
        "rank": 8,
        "title": "Purchasing Supervisor",
        "salaryMin": 13963,
        "salaryMax": 13963,
        "reasons": []
      },
      {
        "rank": 9,
        "title": "Inventory Control Manager",
        "salaryMin": 13614,
        "salaryMax": 13614,
        "reasons": []
      },
      {
        "rank": 10,
        "title": "Demand Planning Manager",
        "salaryMin": 13091,
        "salaryMax": 13091,
        "reasons": []
      }
    ],
    "quality-control": [
      {
        "rank": 1,
        "title": "Quality Director",
        "salaryMin": 19179,
        "salaryMax": 19179,
        "reasons": []
      },
      {
        "rank": 2,
        "title": "Quality Control Manager",
        "salaryMin": 18307,
        "salaryMax": 18307,
        "reasons": []
      },
      {
        "rank": 3,
        "title": "Quality Assurance Executive",
        "salaryMin": 17435,
        "salaryMax": 17435,
        "reasons": []
      },
      {
        "rank": 4,
        "title": "Six Sigma Black Belt",
        "salaryMin": 15111,
        "salaryMax": 15111,
        "reasons": []
      },
      {
        "rank": 5,
        "title": "Product Quality Leader",
        "salaryMin": 13788,
        "salaryMax": 13788,
        "reasons": []
      },
      {
        "rank": 6,
        "title": "Approval Team Manager",
        "salaryMin": 13672,
        "salaryMax": 13672,
        "reasons": []
      },
      {
        "rank": 7,
        "title": "Quality Assurance Supervisor",
        "salaryMin": 13236,
        "salaryMax": 13236,
        "reasons": []
      },
      {
        "rank": 8,
        "title": "Quality Trainer",
        "salaryMin": 12946,
        "salaryMax": 12946,
        "reasons": []
      },
      {
        "rank": 9,
        "title": "Assistant Quality Manager",
        "salaryMin": 12568,
        "salaryMax": 12568,
        "reasons": []
      },
      {
        "rank": 10,
        "title": "Quality Control Analyst",
        "salaryMin": 11958,
        "salaryMax": 11958,
        "reasons": []
      }
    ],
    "real-estate": [
      {
        "rank": 1,
        "title": "Portfolio Manager",
        "salaryMin": 22666,
        "salaryMax": 22666,
        "reasons": []
      },
      {
        "rank": 2,
        "title": "Director of Real Estate",
        "salaryMin": 21794,
        "salaryMax": 21794,
        "reasons": []
      },
      {
        "rank": 3,
        "title": "Shopping Center Manager",
        "salaryMin": 20922,
        "salaryMax": 20922,
        "reasons": []
      },
      {
        "rank": 4,
        "title": "Town Planner",
        "salaryMin": 20486,
        "salaryMax": 20486,
        "reasons": []
      },
      {
        "rank": 5,
        "title": "Property Operations Manager",
        "salaryMin": 20341,
        "salaryMax": 20341,
        "reasons": []
      },
      {
        "rank": 6,
        "title": "Real Estate General Manager",
        "salaryMin": 20051,
        "salaryMax": 20051,
        "reasons": []
      },
      {
        "rank": 7,
        "title": "Commercial Leasing Manager",
        "salaryMin": 19760,
        "salaryMax": 19760,
        "reasons": []
      },
      {
        "rank": 8,
        "title": "Community Development Manager",
        "salaryMin": 18307,
        "salaryMax": 18307,
        "reasons": []
      },
      {
        "rank": 9,
        "title": "Real Estate Project Manager",
        "salaryMin": 17435,
        "salaryMax": 17435,
        "reasons": []
      },
      {
        "rank": 10,
        "title": "Property Manager",
        "salaryMin": 14529,
        "salaryMax": 14529,
        "reasons": []
      }
    ],
    "sales": [
      {
        "rank": 1,
        "title": "Wholesale Manager",
        "salaryMin": 25281,
        "salaryMax": 25281,
        "reasons": []
      },
      {
        "rank": 2,
        "title": "National Sales Manager",
        "salaryMin": 24409,
        "salaryMax": 24409,
        "reasons": []
      },
      {
        "rank": 3,
        "title": "Sales Director",
        "salaryMin": 22666,
        "salaryMax": 22666,
        "reasons": []
      },
      {
        "rank": 4,
        "title": "Sales Executive",
        "salaryMin": 20922,
        "salaryMax": 20922,
        "reasons": []
      },
      {
        "rank": 5,
        "title": "Sales Manager",
        "salaryMin": 20051,
        "salaryMax": 20051,
        "reasons": []
      },
      {
        "rank": 6,
        "title": "National Account Manager",
        "salaryMin": 18307,
        "salaryMax": 18307,
        "reasons": []
      },
      {
        "rank": 7,
        "title": "Head of Direct Sales",
        "salaryMin": 17435,
        "salaryMax": 17435,
        "reasons": []
      },
      {
        "rank": 8,
        "title": "Head of Retail",
        "salaryMin": 17145,
        "salaryMax": 17145,
        "reasons": []
      },
      {
        "rank": 9,
        "title": "Corporate Sales Manager",
        "salaryMin": 16564,
        "salaryMax": 16564,
        "reasons": []
      },
      {
        "rank": 10,
        "title": "Relationship Manager",
        "salaryMin": 16128,
        "salaryMax": 16128,
        "reasons": []
      }
    ],
    "telecommunications": [
      {
        "rank": 1,
        "title": "Telecommunications Manager",
        "salaryMin": 19179,
        "salaryMax": 19179,
        "reasons": []
      },
      {
        "rank": 2,
        "title": "Sales Director",
        "salaryMin": 18307,
        "salaryMax": 18307,
        "reasons": []
      },
      {
        "rank": 3,
        "title": "Chief Technology Officer",
        "salaryMin": 17435,
        "salaryMax": 17435,
        "reasons": []
      },
      {
        "rank": 4,
        "title": "Telecommunication Service Delivery Manager",
        "salaryMin": 14529,
        "salaryMax": 14529,
        "reasons": []
      },
      {
        "rank": 5,
        "title": "Telecommunication Solution Architect",
        "salaryMin": 13817,
        "salaryMax": 13817,
        "reasons": []
      },
      {
        "rank": 6,
        "title": "Telecommunication Consultant",
        "salaryMin": 13469,
        "salaryMax": 13469,
        "reasons": []
      },
      {
        "rank": 7,
        "title": "Telecommunication Project Manager",
        "salaryMin": 13091,
        "salaryMax": 13091,
        "reasons": []
      },
      {
        "rank": 8,
        "title": "Telecommunications Analyst",
        "salaryMin": 12946,
        "salaryMax": 12946,
        "reasons": []
      },
      {
        "rank": 9,
        "title": "Telecommunication Technical Manager",
        "salaryMin": 12800,
        "salaryMax": 12800,
        "reasons": []
      },
      {
        "rank": 10,
        "title": "Access Operation Team Leader",
        "salaryMin": 12365,
        "salaryMax": 12365,
        "reasons": []
      }
    ]
  }
}